Metadata-Version: 2.1
Name: WebScraperAPI
Version: 1.0.3
Summary: A web scraping API that allows users to easily extract data from any website by simply providing the URL. The API utilizes advanced parsing and data storage techniques to ensure accurate and efficient data extraction. The package is easy to install and use, making it perfect for data scientists, researchers, and developers looking to quickly and easily access web data.
Home-page: https://github.com/robbiebusinessacc/WebScraperAPI/
Author: Robbie Walmsley
Author-email: robbiebusinessacc@gmail.com
Classifier: Programming Language :: Python :: 3
Classifier: License :: OSI Approved :: MIT License
Classifier: Operating System :: OS Independent
Requires-Python: >=3.6
License-File: LICENSE
